basepy/__init__.py
basepy/asyncstatsd.py
basepy/cache.py
basepy/config.py
basepy/exceptions.py
basepy/mixins.py
basepy/schedule.py
basepy/statsd.py
basepy/asynclib/__init__.py
basepy/asynclib/datagram.py
basepy/asynclib/threaded.py
basepy/asynclib/timeout.py
basepy/asynclog/__init__.py
basepy/common/__init__.py
basepy/common/log.py
basepy/log/__init__.py
basepy/more/__init__.py
basepy/more/fluent.py
basepy/more/rich_console.py
basepy/more/yaml_config.py
basepy/network/__init__.py
basepy/network/connection.py
basepy-0.5.dist-info/LICENSE
basepy-0.5.dist-info/METADATA
basepy-0.5.dist-info/WHEEL
basepy-0.5.dist-info/top_level.txt
basepy-0.5.dist-info/RECORD
