Metadata-Version: 2.1
Name: basepy
Version: 0.5
Summary: Base library of python 3.6+ and asyncio, include log, config, event, metric etc.
Home-page: https://github.com/pyflow/basepy/
Author: Wei Zhuo
Author-email: zeaphoo@qq.com
License: MIT
Platform: any
Classifier: Development Status :: 4 - Beta
Classifier: Environment :: Web Environment
Classifier: Intended Audience :: Developers
Classifier: License :: OSI Approved :: MIT License
Classifier: Operating System :: OS Independent
Classifier: Programming Language :: Python
Classifier: Programming Language :: Python :: 3
Classifier: Programming Language :: Python :: 3.6
Classifier: Programming Language :: Python :: 3.7
Classifier: Programming Language :: Python :: 3.8
Classifier: Programming Language :: Python :: 3.9
Classifier: Topic :: Software Development :: Libraries :: Python Modules
Requires-Python: >=3.6
License-File: LICENSE
Requires-Dist: toml
Requires-Dist: python-box
Provides-Extra: dev
Requires-Dist: pytest >=3 ; extra == 'dev'
Requires-Dist: mock ; extra == 'dev'
Requires-Dist: pyyaml ; extra == 'dev'
